spacec/__init__.py
spacec/_shared/segmentation.py
spacec/_shared/segmentation_unused.py
spacec/archive/tools_archive.py
spacec/helperfunctions/__init__.py
spacec/helperfunctions/_general.py
spacec/helperfunctions/_qptiff_converter.py
spacec/plotting/__init__.py
spacec/plotting/_general.py
spacec/plotting/_qptiff_converter.py
spacec/plotting/_segmentation.py
spacec/preprocessing/__init__.py
spacec/preprocessing/_general.py
spacec/tools/__init__.py
spacec/tools/_general.py
spacec/tools/_qptiff_converter.py
spacec/tools/_segmentation.py
spacec-0.1.2.dist-info/licenses/LICENSE.txt
spacec-0.1.2.dist-info/METADATA
spacec-0.1.2.dist-info/WHEEL
spacec-0.1.2.dist-info/top_level.txt
spacec-0.1.2.dist-info/RECORD
