Metadata-Version: 2.4
Name: SPACEc
Version: 0.1.2
Summary: SPatial Analysis for CodEX data (SPACEc)
Home-page: https://github.com/yuqiyuqitan/SPACEc
Author: yuqiyuqitan
Author-email: tanyuqi527@gmail.com
License: MIT
Project-URL: Documentation, https://spacec.readthedocs.io/
Project-URL: Source, https://github.com/yuqiyuqitan/SPACEc
Project-URL: Tracker, https://github.com/yuqiyuqitan/SPACEc/issues
Platform: any
Classifier: Development Status :: 4 - Beta
Classifier: Programming Language :: Python
Requires-Python: <3.11,>=3.9
License-File: LICENSE.txt
Requires-Dist: importlib-metadata; python_version < "3.8"
Requires-Dist: tqdm
Requires-Dist: joblib
Requires-Dist: pandas
Requires-Dist: yellowbrick
Requires-Dist: statsmodels
Requires-Dist: scikit-learn
Requires-Dist: scikit-image
Requires-Dist: scanpy
Requires-Dist: networkx
Requires-Dist: tensorly
Requires-Dist: cellpose==3.0.11
Requires-Dist: torch<2.6
Requires-Dist: concave_hull
Requires-Dist: pyFlowSOM
Requires-Dist: TissUUmaps==3.1.1.6
Requires-Dist: Flask==2.0.0
Requires-Dist: Werkzeug==2.3.8
Requires-Dist: GitPython
Requires-Dist: igraph
Requires-Dist: leidenalg; sys_platform != "darwin" or platform_machine != "arm64"
Requires-Dist: louvain; sys_platform != "darwin" or platform_machine != "arm64"
Requires-Dist: python-louvain==0.1
Requires-Dist: matplotlib==3.9
Requires-Dist: panel
Requires-Dist: watchfiles
Requires-Dist: networkx<3.4
Requires-Dist: pyvips
Requires-Dist: openslide-python
Requires-Dist: deepcell; sys_platform != "darwin" or platform_machine != "arm64"
Requires-Dist: geopandas
Requires-Dist: shapely
Requires-Dist: descartes
Provides-Extra: rapids
Requires-Dist: rapids-singlecell[rapids11]; extra == "rapids"
Provides-Extra: stellar
Requires-Dist: torch==1.12.0+cu113; extra == "stellar"
Requires-Dist: torchvision==0.13.0+cu113; extra == "stellar"
Requires-Dist: torchaudio==0.12.0+cu113; extra == "stellar"
Requires-Dist: torch-scatter==2.1.0; extra == "stellar"
Requires-Dist: torch-sparse==0.6.16; extra == "stellar"
Requires-Dist: torch-cluster==1.6.0; extra == "stellar"
Requires-Dist: torch-spline-conv==1.2.1; extra == "stellar"
Requires-Dist: torch-geometric==2.2.0; extra == "stellar"
Provides-Extra: testing
Requires-Dist: setuptools; extra == "testing"
Requires-Dist: pytest; extra == "testing"
Requires-Dist: pytest-cov; extra == "testing"
Dynamic: license-file
